odoo/addons/hr_timesheet_portal/README.rst
odoo/addons/hr_timesheet_portal/__init__.py
odoo/addons/hr_timesheet_portal/__manifest__.py
odoo/addons/hr_timesheet_portal/demo/hr_timesheet_portal.xml
odoo/addons/hr_timesheet_portal/i18n/hr_timesheet_portal.pot
odoo/addons/hr_timesheet_portal/i18n/it.po
odoo/addons/hr_timesheet_portal/readme/CONFIGURE.md
odoo/addons/hr_timesheet_portal/readme/CONTRIBUTORS.md
odoo/addons/hr_timesheet_portal/readme/DESCRIPTION.md
odoo/addons/hr_timesheet_portal/readme/USAGE.md
odoo/addons/hr_timesheet_portal/security/hr_timesheet_portal_security.xml
odoo/addons/hr_timesheet_portal/security/ir.model.access.csv
odoo/addons/hr_timesheet_portal/static/description/icon.png
odoo/addons/hr_timesheet_portal/static/description/index.html
odoo/addons/hr_timesheet_portal/static/img/01_portal_general_view.png
odoo/addons/hr_timesheet_portal/static/img/02_add_timesheet_line.png
odoo/addons/hr_timesheet_portal/static/img/03_edit_timesheet_line.png
odoo/addons/hr_timesheet_portal/static/src/js/hr_timesheet_portal.esm.js
odoo/addons/hr_timesheet_portal/static/src/scss/hr_timesheet_portal.scss
odoo/addons/hr_timesheet_portal/templates/portal.xml
odoo/addons/hr_timesheet_portal/views/hr_employee.xml
odoo_addon_hr_timesheet_portal-17.0.1.0.0.3.dist-info/METADATA
odoo_addon_hr_timesheet_portal-17.0.1.0.0.3.dist-info/WHEEL
odoo_addon_hr_timesheet_portal-17.0.1.0.0.3.dist-info/top_level.txt
odoo_addon_hr_timesheet_portal-17.0.1.0.0.3.dist-info/RECORD
